setup.py
tornado_thumbor_url/__init__.py
tornado_thumbor_url/handlers.py
tornado_thumbor_url.egg-info/PKG-INFO
tornado_thumbor_url.egg-info/SOURCES.txt
tornado_thumbor_url.egg-info/dependency_links.txt
tornado_thumbor_url.egg-info/requires.txt
tornado_thumbor_url.egg-info/top_level.txt