Metadata-Version: 1.0
Name: tornado-thumbor-url
Version: 0.1.0
Summary: tornado-thumbor-url is a python extension to tornado for encrypted thumbor url generation
Home-page: http://github.com/rafaelcaricio/tornado-thumbor-url
Author: Rafael Caricio
Author-email: rafael@caricio.com
License: MIT
Keywords: imaging face detection feature thumbor thumbnail imagemagick pil opencv
Platform: UNKNOWN
Classifier: Development Status :: 4 - Beta
Classifier: Intended Audience :: Developers
Classifier: License :: OSI Approved :: MIT License
Classifier: Natural Language :: English
Classifier: Operating System :: MacOS
Classifier: Operating System :: POSIX :: Linux
Classifier: Programming Language :: Python :: 2.6
Classifier: Topic :: Internet :: WWW/HTTP :: Dynamic Content
Classifier: Topic :: Multimedia :: Graphics :: Presentation
